jupyterlab_terminal_html_log/__init__.py
jupyterlab_terminal_html_log/_version.py
jupyterlab_terminal_html_log-0.1.1.data/data/share/jupyter/labextensions/jupyterlab_terminal_html_log/package.json
jupyterlab_terminal_html_log-0.1.1.data/data/share/jupyter/labextensions/jupyterlab_terminal_html_log/schemas/jupyterlab_terminal_html_log/logger.json
jupyterlab_terminal_html_log-0.1.1.data/data/share/jupyter/labextensions/jupyterlab_terminal_html_log/schemas/jupyterlab_terminal_html_log/package.json.orig
jupyterlab_terminal_html_log-0.1.1.data/data/share/jupyter/labextensions/jupyterlab_terminal_html_log/static/509.fb02946b6625a07cbb8f.js
jupyterlab_terminal_html_log-0.1.1.data/data/share/jupyter/labextensions/jupyterlab_terminal_html_log/static/728.8b13a6ca0e95e0e3b708.js
jupyterlab_terminal_html_log-0.1.1.data/data/share/jupyter/labextensions/jupyterlab_terminal_html_log/static/remoteEntry.ff9841023de98531f0b2.js
jupyterlab_terminal_html_log-0.1.1.data/data/share/jupyter/labextensions/jupyterlab_terminal_html_log/static/style.js
jupyterlab_terminal_html_log-0.1.1.data/data/share/jupyter/labextensions/jupyterlab_terminal_html_log/static/third-party-licenses.json
jupyterlab_terminal_html_log-0.1.1.data/data/share/jupyter/labextensions/jupyterlab_terminal_html_log/install.json
jupyterlab_terminal_html_log-0.1.1.dist-info/METADATA
jupyterlab_terminal_html_log-0.1.1.dist-info/WHEEL
jupyterlab_terminal_html_log-0.1.1.dist-info/licenses/LICENSE
jupyterlab_terminal_html_log-0.1.1.dist-info/RECORD
