Metadata-Version: 2.3
Name: jupyterlab_terminal_html_log
Version: 0.1.1
Summary: Add HTML logging capabilities to JupyterLab's integrated terminal
Project-URL: Homepage, https://github.com/naclomi/jupyterlab-terminal-html-log
Project-URL: Bug Tracker, https://github.com/naclomi/jupyterlab-terminal-html-log/issues
Project-URL: Repository, https://github.com/naclomi/jupyterlab-terminal-html-log.git
Author-email: jupyterlab-terminal-html-log <naomila@uw.edu>
License: BSD 3-Clause License
License-File: LICENSE
Keywords: jupyter,jupyterlab,jupyterlab-extension
Classifier: Framework :: Jupyter
Classifier: Framework :: Jupyter :: JupyterLab
Classifier: Framework :: Jupyter :: JupyterLab :: 4
Classifier: Framework :: Jupyter :: JupyterLab :: Extensions
Classifier: Framework :: Jupyter :: JupyterLab :: Extensions :: Prebuilt
Classifier: License :: OSI Approved :: BSD License
Classifier: Programming Language :: Python
Classifier: Programming Language :: Python :: 3
Classifier: Programming Language :: Python :: 3.8
Classifier: Programming Language :: Python :: 3.9
Classifier: Programming Language :: Python :: 3.10
Classifier: Programming Language :: Python :: 3.11
Classifier: Programming Language :: Python :: 3.12
Requires-Python: >=3.8
